defi_trainer
