Metadata-Version: 1.0
Name: defi-trainer
Version: 1.1b
Summary: DefiTrainer is a light-weight definition and fact trainer
Home-page: http://blog.stevenmohr.de/projects/defitrainer/
Author: Steven Mohr
Author-email: steven@stevenmohr.de
License: GPL v3
Keywords: learning studies school trainer
Platform: UNKNOWN
